ros_command/__init__.py
ros_command/_version.py
ros_command/build_status_display.py
ros_command/build_tool.py
ros_command/command_lib.py
ros_command/completion.py
ros_command/packages.py
ros_command/ros_command_setup.bash
ros_command/terminal_display.py
ros_command/util.py
ros_command/commands/get_current_setup_bash.py
ros_command/commands/get_ros_command_bash.py
ros_command/commands/get_ros_directory.py
ros_command/commands/rosbuild.py
ros_command/commands/rosclean.py
ros_command/commands/rosdep_install.py
ros_command/commands/rosexecute.py
ros_command/commands/rosinterface.py
ros_command/commands/roslaunch.py
ros_command/commands/rosrun.py
ros_command-0.1.0.dist-info/METADATA
ros_command-0.1.0.dist-info/WHEEL
ros_command-0.1.0.dist-info/entry_points.txt
ros_command-0.1.0.dist-info/licenses/LICENSE
ros_command-0.1.0.dist-info/RECORD
