Metadata-Version: 2.3
Name: ros_command
Version: 0.1.0
Summary: Unifying the ROS command line tools
Project-URL: Homepage, https://github.com/MetroRobots/ros_command
Project-URL: Bug Tracker, https://github.com/MetroRobots/ros_command/issues
Author-email: "David V. Lu!!" <davidvlu@gmail.com>
Maintainer-email: "David V. Lu!!" <davidvlu@gmail.com>
License-File: LICENSE
Requires-Python: >=3.8
Requires-Dist: argcomplete
Requires-Dist: argparse
Requires-Dist: betsy-ros
Requires-Dist: blessed
Requires-Dist: click
Requires-Dist: pyyaml
